LICENSE
README.md
setup.py
alephvault/evm_http_storage/__init__.py
alephvault/evm_http_storage/validation.py
alephvault/evm_http_storage/core/__init__.py
alephvault/evm_http_storage/core/contract_handler.py
alephvault/evm_http_storage/core/decorators.py
alephvault/evm_http_storage/core/grabber.py
alephvault/evm_http_storage/core/processor.py
alephvault/evm_http_storage/core/common/__init__.py
alephvault/evm_http_storage/core/common/token/__init__.py
alephvault/evm_http_storage/core/common/token/abi.py
alephvault/evm_http_storage/core/common/token/erc1155handler.py
alephvault/evm_http_storage/core/common/token/erc20handler.py
alephvault/evm_http_storage/core/common/token/erc721handler.py
alephvault/evm_http_storage/core/common/token/shortcuts.py
alephvault/evm_http_storage/methods/__init__.py
alephvault/evm_http_storage/methods/worker.py
alephvault/evm_http_storage/methods/common/__init__.py
alephvault/evm_http_storage/methods/common/erc1155.py
alephvault/evm_http_storage/methods/common/erc20.py
alephvault/evm_http_storage/methods/common/erc721.py
alephvault/evm_http_storage/schemas/__init__.py
alephvault/evm_http_storage/schemas/contracts.py
alephvault/evm_http_storage/schemas/resources.py
alephvault/evm_http_storage/schemas/common/__init__.py
alephvault/evm_http_storage/schemas/common/erc1155.py
alephvault/evm_http_storage/schemas/common/erc20.py
alephvault/evm_http_storage/schemas/common/erc721.py
alephvault_evm_events_http_mongodb_storage.egg-info/PKG-INFO
alephvault_evm_events_http_mongodb_storage.egg-info/SOURCES.txt
alephvault_evm_events_http_mongodb_storage.egg-info/dependency_links.txt
alephvault_evm_events_http_mongodb_storage.egg-info/requires.txt
alephvault_evm_events_http_mongodb_storage.egg-info/top_level.txt
samples/__init__.py
samples/server.py